[
  {
    "memory": 2,
    "timestamp": "11/09 03:26"
  },
  {
    "memory": 35,
    "timestamp": "12/02 23:54"
  },
  {
    "memory": 100,
    "timestamp": "09/19 08:52"
  },
  {
    "memory": 90,
    "timestamp": "05/21 20:49"
  },
  {
    "memory": 89,
    "timestamp": "08/05 07:28"
  },
  {
    "memory": 42,
    "timestamp": "06/30 10:05"
  },
  {
    "memory": 14,
    "timestamp": "08/04 15:55"
  },
  {
    "memory": 45,
    "timestamp": "11/30 14:36"
  },
  {
    "memory": 26,
    "timestamp": "12/16 06:49"
  },
  {
    "memory": 71,
    "timestamp": "06/12 21:12"
  },
  {
    "memory": 61,
    "timestamp": "06/10 09:57"
  },
  {
    "memory": 38,
    "timestamp": "07/08 20:23"
  },
  {
    "memory": 55,
    "timestamp": "02/08 08:46"
  },
  {
    "memory": 22,
    "timestamp": "05/02 12:09"
  },
  {
    "memory": 71,
    "timestamp": "08/16 15:11"
  },
  {
    "memory": 24,
    "timestamp": "07/10 19:00"
  },
  {
    "memory": 73,
    "timestamp": "11/10 18:15"
  },
  {
    "memory": 23,
    "timestamp": "02/01 12:07"
  },
  {
    "memory": 37,
    "timestamp": "03/19 04:02"
  },
  {
    "memory": 56,
    "timestamp": "12/19 17:14"
  }
]
